bareos/VERSION.txt
bareos/__init__.py
bareos/exceptions.py
bareos/bsock/__init__.py
bareos/bsock/bsock.py
bareos/bsock/bsockjson.py
bareos/bsock/connectiontype.py
bareos/bsock/constants.py
bareos/bsock/directorconsole.py
bareos/bsock/directorconsolejson.py
bareos/bsock/filedaemon.py
bareos/bsock/lowlevel.py
bareos/bsock/protocolmessageids.py
bareos/bsock/protocolmessages.py
bareos/bsock/protocolversions.py
bareos/bsock/tlsversionparser.py
bareos/util/__init__.py
bareos/util/argparse.py
bareos/util/bareosbase64.py
bareos/util/password.py
bareos/util/path.py
bareos/util/version.py
python_bareos-25.0.1.data/scripts/bareos-fd-connect.py
python_bareos-25.0.1.data/scripts/bconsole-json.py
python_bareos-25.0.1.data/scripts/bconsole.py
python_bareos-25.0.1.dist-info/licenses/LICENSE.txt
python_bareos-25.0.1.dist-info/METADATA
python_bareos-25.0.1.dist-info/WHEEL
python_bareos-25.0.1.dist-info/top_level.txt
python_bareos-25.0.1.dist-info/RECORD
