Metadata-Version: 2.4
Name: python-bareos
Version: 25.0.1
Summary: Client library and tools for Bareos console access.
Home-page: https://github.com/bareos/bareos/
Author: Bareos Team
Author-email: packager@bareos.com
License: AGPLv3
Keywords: bareos
Classifier: Development Status :: 5 - Production/Stable
Classifier: License :: OSI Approved :: GNU Affero General Public License v3
Classifier: Operating System :: OS Independent
Classifier: Programming Language :: Python
Classifier: Topic :: System :: Archiving :: Backup
Requires-Python: >=3.6
License-File: LICENSE.txt
Provides-Extra: configfile
Requires-Dist: configargparse; extra == "configfile"
Dynamic: author
Dynamic: author-email
Dynamic: classifier
Dynamic: description
Dynamic: description-content-type
Dynamic: home-page
Dynamic: keywords
Dynamic: license
Dynamic: license-file
Dynamic: provides-extra
Dynamic: requires-python
Dynamic: summary
